{
	"name": "PL_INJEST_CASES_DEATHS_DATA",
	"properties": {
		"activities": [
			{
				"name": "Copy CASES AND DEATH",
				"type": "Copy",
				"dependsOn": [],
				"policy": {
					"timeout": "0.12:00:00",
					"retry": 0,
					"retryIntervalInSeconds": 30,
					"secureOutput": false,
					"secureInput": false
				},
				"userProperties": [],
				"typeProperties": {
					"source": {
						"type": "DelimitedTextSource",
						"storeSettings": {
							"type": "HttpReadSettings",
							"requestMethod": "GET"
						},
						"formatSettings": {
							"type": "DelimitedTextReadSettings"
						}
					},
					"sink": {
						"type": "DelimitedTextSink",
						"storeSettings": {
							"type": "AzureBlobFSWriteSettings"
						},
						"formatSettings": {
							"type": "DelimitedTextWriteSettings",
							"quoteAllText": true,
							"fileExtension": ".txt"
						}
					},
					"enableStaging": false,
					"translator": {
						"type": "TabularTranslator",
						"typeConversion": true,
						"typeConversionSettings": {
							"allowDataTruncation": true,
							"treatBooleanAsNumber": false
						}
					}
				},
				"inputs": [
					{
						"referenceName": "DS_CASES_DEATH_RAW_CSV_HTTP",
						"type": "DatasetReference",
						"parameters": {
							"Relativeurl": {
								"value": "@variables('SourceRelativeUrl')",
								"type": "Expression"
							}
						}
					}
				],
				"outputs": [
					{
						"referenceName": "DS_CASES_DEATH_RAW_DL",
						"type": "DatasetReference",
						"parameters": {
							"Filename": {
								"value": "@variables('SInkFileName')",
								"type": "Expression"
							}
						}
					}
				]
			}
		],
		"variables": {
			"SourceRelativeUrl": {
				"type": "String",
				"defaultValue": "cloudboxacademy/covid19/main/ecdc_data/hospital_admissions.csv"
			},
			"SInkFileName": {
				"type": "String",
				"defaultValue": "hospitalAdmission.csv"
			}
		},
		"folder": {
			"name": "COVID PROJECT"
		},
		"annotations": []
	}
}